fastapi_simple_auth/__init__.py
fastapi_simple_auth/captcha.py
fastapi_simple_auth/cron.py
fastapi_simple_auth/crud.py
fastapi_simple_auth/db.py
fastapi_simple_auth/envmail.py
fastapi_simple_auth/exceptions.py
fastapi_simple_auth/jwt.py
fastapi_simple_auth/models.py
fastapi_simple_auth/passwordstrength.py
fastapi_simple_auth/pub.py
fastapi_simple_auth/router.py
fastapi_simple_auth/schemas.py
fastapi_simple_auth/session.py
fastapi_simple_auth/settings.py
fastapi_simple_auth/startup.py
fastapi_simple_auth/str2dict.py
fastapi_simple_auth/templates.py
fastapi_simple_auth/verification.py
fastapi_simple_auth/alembic/README
fastapi_simple_auth/alembic/env.py
fastapi_simple_auth/alembic/script.py.mako
fastapi_simple_auth/alembic/versions/9a3f872373f4_initial.py
fastapi_simple_auth/cli/__init__.py
fastapi_simple_auth/cli/simpleauth.py
fastapi_simple_auth/templates/afterlogin.html
fastapi_simple_auth/templates/base.html
fastapi_simple_auth/templates/login.html
fastapi_simple_auth/templates/profile.html
fastapi_simple_auth/templates/recover.html
fastapi_simple_auth/templates/recover_code.html
fastapi_simple_auth/templates/register.html
fastapi_simple_auth/templates/verify-email.html
fastapi_simple_auth/templates/email/change-email.html
fastapi_simple_auth/templates/email/confirm-email.html
fastapi_simple_auth/templates/email/recover.html
fastapi_simple_auth/views/__init__.py
fastapi_simple_auth/views/jwt.py
fastapi_simple_auth/views/login.py
fastapi_simple_auth/views/profile.py
fastapi_simple_auth/views/recover.py
fastapi_simple_auth/views/settingsjs.py
fastapi_simple_auth/views/signup.py
fastapi_simple_auth/views/verify.py
fastapi_simple_auth-0.0.9.dist-info/METADATA
fastapi_simple_auth-0.0.9.dist-info/WHEEL
fastapi_simple_auth-0.0.9.dist-info/entry_points.txt
fastapi_simple_auth-0.0.9.dist-info/licenses/LICENSE
fastapi_simple_auth-0.0.9.dist-info/RECORD
